---
title: Technical Appendix
---

The topics covered here exceed the level of knowledge required to benefit from the course, however provide a more technical explanation of some of the concepts that can help you understand your code's performance.

**Contents**

- [Viewing Python's ByteCode](#viewing-pythons-bytecode)
- []()
- []()

## Viewing Python's ByteCode

You can use `dis` to view the bytecode generated by Python, the amount of bytecode more strongly correlates with how much code is being executed by the Python interpreter and hence how long it may take to execute. However, this is a crude proxy as it does not account for whether functions that are called and whether those functions are implemented using Python or C.

The pure Python search compiles to 82 lines of byte-code.

```python
import dis

def manualSearch():
    ls = generateInputs()
    ct = 0
    for i in range(0, int(N*M), M):
        for j in range(0, len(ls)):
            if ls[j] == i:
                ct += 1
                break

dis.dis(manualSearch)
```
```output
 11           0 LOAD_GLOBAL              0 (generateInputs)
              2 CALL_FUNCTION            0
              4 STORE_FAST               0 (ls)

 12           6 LOAD_CONST               1 (0)
              8 STORE_FAST               1 (ct)

 13          10 LOAD_GLOBAL              1 (range)
             12 LOAD_CONST               1 (0)
             14 LOAD_GLOBAL              2 (int)
             16 LOAD_GLOBAL              3 (N)
             18 LOAD_GLOBAL              4 (M)
             20 BINARY_MULTIPLY
             22 CALL_FUNCTION            1
             24 LOAD_GLOBAL              4 (M)
             26 CALL_FUNCTION            3
             28 GET_ITER
        >>   30 FOR_ITER                24 (to 80)
             32 STORE_FAST               2 (i)

 14          34 LOAD_GLOBAL              1 (range)
             36 LOAD_CONST               1 (0)
             38 LOAD_GLOBAL              5 (len)
             40 LOAD_FAST                0 (ls)
             42 CALL_FUNCTION            1
             44 CALL_FUNCTION            2
             46 GET_ITER
        >>   48 FOR_ITER                14 (to 78)
             50 STORE_FAST               3 (j)

 15          52 LOAD_FAST                0 (ls)
             54 LOAD_FAST                3 (j)
             56 BINARY_SUBSCR
             58 LOAD_FAST                2 (i)
             60 COMPARE_OP               2 (==)
             62 POP_JUMP_IF_FALSE       38 (to 76)

 16          64 LOAD_FAST                1 (ct)
             66 LOAD_CONST               2 (1)
             68 INPLACE_ADD
             70 STORE_FAST               1 (ct)

 17          72 POP_TOP
             74 JUMP_FORWARD             1 (to 78)

 15     >>   76 JUMP_ABSOLUTE           24 (to 48)
        >>   78 JUMP_ABSOLUTE           15 (to 30)

 13     >>   80 LOAD_CONST               0 (None)
             82 RETURN_VALUE
```

Whereas the `in` variant only compiles to 54.

```python
import dis

def operatorSearch():
    ls = generateInputs()
    ct = 0
    for i in range(0, int(N*M), M):
        if i in ls:
            ct += 1

dis.dis(operatorSearch)
```
```output
  4           0 LOAD_GLOBAL              0 (generateInputs)
              2 CALL_FUNCTION            0
              4 STORE_FAST               0 (ls)

  5           6 LOAD_CONST               1 (0)
              8 STORE_FAST               1 (ct)

  6          10 LOAD_GLOBAL              1 (range)
             12 LOAD_CONST               1 (0)
             14 LOAD_GLOBAL              2 (int)
             16 LOAD_GLOBAL              3 (N)
             18 LOAD_GLOBAL              4 (M)
             20 BINARY_MULTIPLY
             22 CALL_FUNCTION            1
             24 LOAD_GLOBAL              4 (M)
             26 CALL_FUNCTION            3
             28 GET_ITER
        >>   30 FOR_ITER                10 (to 52)
             32 STORE_FAST               2 (i)

  7          34 LOAD_FAST                2 (i)
             36 LOAD_FAST                0 (ls)
             38 CONTAINS_OP              0
             40 POP_JUMP_IF_FALSE       25 (to 50)

  8          42 LOAD_FAST                1 (ct)
             44 LOAD_CONST               2 (1)
             46 INPLACE_ADD
             48 STORE_FAST               1 (ct)
        >>   50 JUMP_ABSOLUTE           15 (to 30)

  6     >>   52 LOAD_CONST               0 (None)
             54 RETURN_VALUE
```

## 

## 